vector_pipelines/__init__.py
vector_pipelines/cli/__init__.py
vector_pipelines/cli/app.py
vector_pipelines/cli/service.py
vector_pipelines/components/__init__.py
vector_pipelines/components/factory.py
vector_pipelines/components/init.py
vector_pipelines/components/service.py
vector_pipelines/components/embeddings/__init__.py
vector_pipelines/components/embeddings/base.py
vector_pipelines/components/embeddings/sentence_transformers.py
vector_pipelines/components/embeddings/service.py
vector_pipelines/grpc/__init__.py
vector_pipelines/grpc/embeddings_pb2.py
vector_pipelines/grpc/embeddings_pb2.pyi
vector_pipelines/grpc/embeddings_pb2_grpc.py
vector_pipelines/proto/embeddings.proto
vector_pipelines/utils/__init__.py
vector_pipelines/utils/imports.py
vector_pipelines-0.0.3.dist-info/METADATA
vector_pipelines-0.0.3.dist-info/WHEEL
vector_pipelines-0.0.3.dist-info/entry_points.txt
vector_pipelines-0.0.3.dist-info/licenses/LICENSE
vector_pipelines-0.0.3.dist-info/RECORD
